dbis_er_diagram-1.1.2.dist-info/licenses/LICENSE
erdiagram/__init__.py
erdiagram/drawing.py
erdiagram/er.py
erdiagram/grading.py
erdiagram/merging.py
erdiagram/node_type.py
dbis_er_diagram-1.1.2.dist-info/METADATA
dbis_er_diagram-1.1.2.dist-info/WHEEL
dbis_er_diagram-1.1.2.dist-info/top_level.txt
dbis_er_diagram-1.1.2.dist-info/RECORD
